setup.cfg
setup.py
wnsresolver/__init__.py
wnsresolver.egg-info/PKG-INFO
wnsresolver.egg-info/SOURCES.txt
wnsresolver.egg-info/dependency_links.txt
wnsresolver.egg-info/requires.txt
wnsresolver.egg-info/top_level.txt