Metadata-Version: 1.1
Name: wnsresolver
Version: 0.0.9
Summary: Wallet Name Resolver Library
Home-page: https://github.com/netkicorp/wns-resolver
Author: mdavid
Author-email: opensource@netki.com
License: BSD
Download-URL: https://github.com/netkicorp/wns-resolver/tarball/0.0.9
Platform: any
